[
  {
    "meeting_id": 50146,
    "meeting_category": "국회",
    "deasu": "21",
    "meeting_specification": "소위원회",
    "commitee": "정무위원회-예산결산심사소위원회",
    "number_of_meetings": 381,
    "chasu": 1,
    "meeting_date": "2020년8월31일(월)"
  },
  {
    "meeting_id": 50236,
    "meeting_category": "국회",
    "deasu": "21",
    "meeting_specification": "소위원회",
    "commitee": "정무위원회-법안심사제1소위원회",
    "number_of_meetings": 382,
    "chasu": 1,
    "meeting_date": "2020년9월22일(화)"
  },
  {
    "meeting_id": 50245,
    "meeting_category": "국회",
    "deasu": "21",
    "meeting_specification": "소위원회",
    "commitee": "정무위원회-법안심사제2소위원회",
    "number_of_meetings": 382,
    "chasu": 1,
    "meeting_date": "2020년9월23일(수)"
  },
  {
    "meeting_id": 50412,
    "meeting_category": "국회",
    "deasu": "21",
    "meeting_specification": "소위원회",
    "commitee": "정무위원회-예산결산심사소위원회",
    "number_of_meetings": 382,
    "chasu": 1,
    "meeting_date": "2020년11월9일(월)"
  },
  {
    "meeting_id": 50413,
    "meeting_category": "국회",
    "deasu": "21",
    "meeting_specification": "소위원회",
    "commitee": "정무위원회-예산결산심사소위원회",
    "number_of_meetings": 382,
    "chasu": 2,
    "meeting_date": "2020년11월10일(화)"
  },
  {
    "meeting_id": 50530,
    "meeting_category": "국회",
    "deasu": "21",
    "meeting_specification": "소위원회",
    "commitee": "정무위원회-법안심사제1소위원회",
    "number_of_meetings": 382,
    "chasu": 2,
    "meeting_date": "2020년11월24일(화)"
  },
  {
    "meeting_id": 50537,
    "meeting_category": "국회",
    "deasu": "21",
    "meeting_specification": "소위원회",
    "commitee": "정무위원회-법안심사제2소위원회",
    "number_of_meetings": 382,
    "chasu": 2,
    "meeting_date": "2020년11월25일(수)"
  },
  {
    "meeting_id": 50588,
    "meeting_category": "국회",
    "deasu": "21",
    "meeting_specification": "소위원회",
    "commitee": "정무위원회-법안심사제2소위원회",
    "number_of_meetings": 382,
    "chasu": 3,
    "meeting_date": "2020년12월1일(화)"
  },
  {
    "meeting_id": 50603,
    "meeting_category": "국회",
    "deasu": "21",
    "meeting_specification": "소위원회",
    "commitee": "정무위원회-법안심사제1소위원회",
    "number_of_meetings": 382,
    "chasu": 3,
    "meeting_date": "2020년12월2일(수)"
  },
  {
    "meeting_id": 50616,
    "meeting_category": "국회",
    "deasu": "21",
    "meeting_specification": "소위원회",
    "commitee": "정무위원회-법안심사제2소위원회",
    "number_of_meetings": 382,
    "chasu": 4,
    "meeting_date": "2020년12월3일(목)"
  },
  {
    "meeting_id": 50617,
    "meeting_category": "국회",
    "deasu": "21",
    "meeting_specification": "소위원회",
    "commitee": "정무위원회-법안심사제1소위원회",
    "number_of_meetings": 382,
    "chasu": 4,
    "meeting_date": "2020년12월3일(목)"
  },
  {
    "meeting_id": 50636,
    "meeting_category": "국회",
    "deasu": "21",
    "meeting_specification": "소위원회",
    "commitee": "정무위원회-법안심사제1소위원회",
    "number_of_meetings": 382,
    "chasu": 5,
    "meeting_date": "2020년12월7일(월)"
  },
  {
    "meeting_id": 50824,
    "meeting_category": "국회",
    "deasu": "21",
    "meeting_specification": "소위원회",
    "commitee": "정무위원회-법안심사제2소위원회",
    "number_of_meetings": 384,
    "chasu": 1,
    "meeting_date": "2021년2월24일(수)"
  },
  {
    "meeting_id": 50825,
    "meeting_category": "국회",
    "deasu": "21",
    "meeting_specification": "소위원회",
    "commitee": "정무위원회-법안심사제1소위원회",
    "number_of_meetings": 384,
    "chasu": 1,
    "meeting_date": "2021년2월23일(화)"
  },
  {
    "meeting_id": 50894,
    "meeting_category": "국회",
    "deasu": "21",
    "meeting_specification": "소위원회",
    "commitee": "정무위원회-법안심사제2소위원회",
    "number_of_meetings": 385,
    "chasu": 1,
    "meeting_date": "2021년3월18일(목)"
  },
  {
    "meeting_id": 50895,
    "meeting_category": "국회",
    "deasu": "21",
    "meeting_specification": "소위원회",
    "commitee": "정무위원회-법안심사제1소위원회",
    "number_of_meetings": 385,
    "chasu": 1,
    "meeting_date": "2021년3월17일(수)"
  },
  {
    "meeting_id": 50918,
    "meeting_category": "국회",
    "deasu": "21",
    "meeting_specification": "소위원회",
    "commitee": "정무위원회-법안심사제1소위원회",
    "number_of_meetings": 385,
    "chasu": 2,
    "meeting_date": "2021년3월22일(월)"
  },
  {
    "meeting_id": 50936,
    "meeting_category": "국회",
    "deasu": "21",
    "meeting_specification": "소위원회",
    "commitee": "정무위원회-법안심사제2소위원회",
    "number_of_meetings": 385,
    "chasu": 3,
    "meeting_date": "2021년3월24일(수)"
  },
  {
    "meeting_id": 50938,
    "meeting_category": "국회",
    "deasu": "21",
    "meeting_specification": "소위원회",
    "commitee": "정무위원회-법안심사제2소위원회",
    "number_of_meetings": 385,
    "chasu": 2,
    "meeting_date": "2021년3월23일(화)"
  },
  {
    "meeting_id": 50944,
    "meeting_category": "국회",
    "deasu": "21",
    "meeting_specification": "소위원회",
    "commitee": "정무위원회-법안심사제2소위원회",
    "number_of_meetings": 385,
    "chasu": 4,
    "meeting_date": "2021년3월31일(수)"
  },
  {
    "meeting_id": 50945,
    "meeting_category": "국회",
    "deasu": "21",
    "meeting_specification": "소위원회",
    "commitee": "정무위원회-법안심사제2소위원회",
    "number_of_meetings": 386,
    "chasu": 1,
    "meeting_date": "2021년4월2일(금)"
  },
  {
    "meeting_id": 50946,
    "meeting_category": "국회",
    "deasu": "21",
    "meeting_specification": "소위원회",
    "commitee": "정무위원회-법안심사제2소위원회",
    "number_of_meetings": 386,
    "chasu": 2,
    "meeting_date": "2021년4월12일(월)"
  },
  {
    "meeting_id": 50947,
    "meeting_category": "국회",
    "deasu": "21",
    "meeting_specification": "소위원회",
    "commitee": "정무위원회-법안심사제2소위원회",
    "number_of_meetings": 386,
    "chasu": 3,
    "meeting_date": "2021년4월13일(화)"
  },
  {
    "meeting_id": 50949,
    "meeting_category": "국회",
    "deasu": "21",
    "meeting_specification": "소위원회",
    "commitee": "정무위원회-법안심사제2소위원회",
    "number_of_meetings": 386,
    "chasu": 4,
    "meeting_date": "2021년4월14일(수)"
  },
  {
    "meeting_id": 50979,
    "meeting_category": "국회",
    "deasu": "21",
    "meeting_specification": "소위원회",
    "commitee": "정무위원회-법안심사제1소위원회",
    "number_of_meetings": 386,
    "chasu": 1,
    "meeting_date": "2021년4월26일(월)"
  },
  {
    "meeting_id": 51084,
    "meeting_category": "국회",
    "deasu": "21",
    "meeting_specification": "소위원회",
    "commitee": "정무위원회-법안심사제1소위원회",
    "number_of_meetings": 388,
    "chasu": 1,
    "meeting_date": "2021년6월23일(수)"
  },
  {
    "meeting_id": 51114,
    "meeting_category": "국회",
    "deasu": "21",
    "meeting_specification": "소위원회",
    "commitee": "정무위원회-법안심사제2소위원회",
    "number_of_meetings": 388,
    "chasu": 1,
    "meeting_date": "2021년6월30일(수)"
  },
  {
    "meeting_id": 51156,
    "meeting_category": "국회",
    "deasu": "21",
    "meeting_specification": "소위원회",
    "commitee": "정무위원회-법안심사제1소위원회",
    "number_of_meetings": 389,
    "chasu": 1,
    "meeting_date": "2021년7월20일(화)"
  },
  {
    "meeting_id": 51230,
    "meeting_category": "국회",
    "deasu": "21",
    "meeting_specification": "소위원회",
    "commitee": "정무위원회-예산결산심사소위원회",
    "number_of_meetings": 390,
    "chasu": 1,
    "meeting_date": "2021년8월30일(월)"
  },
  {
    "meeting_id": 51316,
    "meeting_category": "국회",
    "deasu": "21",
    "meeting_specification": "소위원회",
    "commitee": "정무위원회-법안심사제1소위원회",
    "number_of_meetings": 391,
    "chasu": 1,
    "meeting_date": "2021년9월28일(화)"
  },
  {
    "meeting_id": 51318,
    "meeting_category": "국회",
    "deasu": "21",
    "meeting_specification": "소위원회",
    "commitee": "정무위원회-법안심사제2소위원회",
    "number_of_meetings": 391,
    "chasu": 1,
    "meeting_date": "2021년9월28일(화)"
  },
  {
    "meeting_id": 51449,
    "meeting_category": "국회",
    "deasu": "21",
    "meeting_specification": "소위원회",
    "commitee": "정무위원회-예산결산심사소위원회",
    "number_of_meetings": 391,
    "chasu": 2,
    "meeting_date": "2021년11월11일(목)"
  },
  {
    "meeting_id": 51456,
    "meeting_category": "국회",
    "deasu": "21",
    "meeting_specification": "소위원회",
    "commitee": "정무위원회-예산결산심사소위원회",
    "number_of_meetings": 391,
    "chasu": 1,
    "meeting_date": "2021년11월10일(수)"
  },
  {
    "meeting_id": 51495,
    "meeting_category": "국회",
    "deasu": "21",
    "meeting_specification": "소위원회",
    "commitee": "정무위원회-예산결산심사소위원회",
    "number_of_meetings": 391,
    "chasu": 3,
    "meeting_date": "2021년11월15일(월)"
  },
  {
    "meeting_id": 51528,
    "meeting_category": "국회",
    "deasu": "21",
    "meeting_specification": "소위원회",
    "commitee": "정무위원회-법안심사제1소위원회",
    "number_of_meetings": 391,
    "chasu": 2,
    "meeting_date": "2021년11월17일(수)"
  },
  {
    "meeting_id": 51539,
    "meeting_category": "국회",
    "deasu": "21",
    "meeting_specification": "소위원회",
    "commitee": "정무위원회-법안심사제2소위원회",
    "number_of_meetings": 391,
    "chasu": 2,
    "meeting_date": "2021년11월18일(목)"
  },
  {
    "meeting_id": 51548,
    "meeting_category": "국회",
    "deasu": "21",
    "meeting_specification": "소위원회",
    "commitee": "정무위원회-법안심사제1소위원회",
    "number_of_meetings": 391,
    "chasu": 3,
    "meeting_date": "2021년11월23일(화)"
  },
  {
    "meeting_id": 51553,
    "meeting_category": "국회",
    "deasu": "21",
    "meeting_specification": "소위원회",
    "commitee": "정무위원회-법안심사제2소위원회",
    "number_of_meetings": 391,
    "chasu": 3,
    "meeting_date": "2021년11월24일(수)"
  },
  {
    "meeting_id": 51910,
    "meeting_category": "국회",
    "deasu": "21",
    "meeting_specification": "소위원회",
    "commitee": "정무위원회-예산결산심사소위원회",
    "number_of_meetings": 397,
    "chasu": 1,
    "meeting_date": "2022년5월17일(화)"
  },
  {
    "meeting_id": 52072,
    "meeting_category": "국회",
    "deasu": "21",
    "meeting_specification": "소위원회",
    "commitee": "정무위원회-예산결산심사소위원회",
    "number_of_meetings": 399,
    "chasu": 1,
    "meeting_date": "2022년8월23일(화)"
  },
  {
    "meeting_id": 52304,
    "meeting_category": "국회",
    "deasu": "21",
    "meeting_specification": "소위원회",
    "commitee": "정무위원회-예산결산심사소위원회",
    "number_of_meetings": 400,
    "chasu": 1,
    "meeting_date": "2022년11월3일(목)"
  },
  {
    "meeting_id": 52316,
    "meeting_category": "국회",
    "deasu": "21",
    "meeting_specification": "소위원회",
    "commitee": "정무위원회-예산결산심사소위원회",
    "number_of_meetings": 400,
    "chasu": 2,
    "meeting_date": "2022년11월7일(월)"
  },
  {
    "meeting_id": 52386,
    "meeting_category": "국회",
    "deasu": "21",
    "meeting_specification": "소위원회",
    "commitee": "정무위원회-법안심사제1소위원회",
    "number_of_meetings": 400,
    "chasu": 1,
    "meeting_date": "2022년11월15일(화)"
  },
  {
    "meeting_id": 52420,
    "meeting_category": "국회",
    "deasu": "21",
    "meeting_specification": "소위원회",
    "commitee": "정무위원회-법안심사제2소위원회",
    "number_of_meetings": 400,
    "chasu": 1,
    "meeting_date": "2022년11월17일(목)"
  },
  {
    "meeting_id": 52454,
    "meeting_category": "국회",
    "deasu": "21",
    "meeting_specification": "소위원회",
    "commitee": "정무위원회-법안심사제1소위원회",
    "number_of_meetings": 400,
    "chasu": 2,
    "meeting_date": "2022년11월22일(화)"
  },
  {
    "meeting_id": 52487,
    "meeting_category": "국회",
    "deasu": "21",
    "meeting_specification": "소위원회",
    "commitee": "정무위원회-법안심사제2소위원회",
    "number_of_meetings": 400,
    "chasu": 2,
    "meeting_date": "2022년11월24일(목)"
  },
  {
    "meeting_id": 52488,
    "meeting_category": "국회",
    "deasu": "21",
    "meeting_specification": "소위원회",
    "commitee": "정무위원회-예산결산심사소위원회",
    "number_of_meetings": 400,
    "chasu": 3,
    "meeting_date": "2022년11월24일(목)"
  },
  {
    "meeting_id": 52631,
    "meeting_category": "국회",
    "deasu": "21",
    "meeting_specification": "소위원회",
    "commitee": "정무위원회-법안심사제1소위원회",
    "number_of_meetings": 401,
    "chasu": 1,
    "meeting_date": "2022년12월26일(월)"
  },
  {
    "meeting_id": 52640,
    "meeting_category": "국회",
    "deasu": "21",
    "meeting_specification": "소위원회",
    "commitee": "정무위원회-법안심사제2소위원회",
    "number_of_meetings": 401,
    "chasu": 1,
    "meeting_date": "2022년12월28일(수)"
  },
  {
    "meeting_id": 52651,
    "meeting_category": "국회",
    "deasu": "21",
    "meeting_specification": "소위원회",
    "commitee": "정무위원회-법안심사제1소위원회",
    "number_of_meetings": 402,
    "chasu": 1,
    "meeting_date": "2023년1월16일(월)"
  },
  {
    "meeting_id": 52656,
    "meeting_category": "국회",
    "deasu": "21",
    "meeting_specification": "소위원회",
    "commitee": "정무위원회-법안심사제2소위원회",
    "number_of_meetings": 402,
    "chasu": 1,
    "meeting_date": "2023년1월18일(수)"
  },
  {
    "meeting_id": 52756,
    "meeting_category": "국회",
    "deasu": "21",
    "meeting_specification": "소위원회",
    "commitee": "정무위원회-법안심사제1소위원회",
    "number_of_meetings": 403,
    "chasu": 1,
    "meeting_date": "2023년2월27일(월)"
  },
  {
    "meeting_id": 52761,
    "meeting_category": "국회",
    "deasu": "21",
    "meeting_specification": "소위원회",
    "commitee": "정무위원회-법안심사제1소위원회",
    "number_of_meetings": 404,
    "chasu": 1,
    "meeting_date": "2023년3월9일(목)"
  },
  {
    "meeting_id": 52820,
    "meeting_category": "국회",
    "deasu": "21",
    "meeting_specification": "소위원회",
    "commitee": "정무위원회-법안심사제1소위원회",
    "number_of_meetings": 404,
    "chasu": 2,
    "meeting_date": "2023년3월28일(화)"
  },
  {
    "meeting_id": 52832,
    "meeting_category": "국회",
    "deasu": "21",
    "meeting_specification": "소위원회",
    "commitee": "정무위원회-법안심사제2소위원회",
    "number_of_meetings": 404,
    "chasu": 1,
    "meeting_date": "2023년3월30일(목)"
  },
  {
    "meeting_id": 52885,
    "meeting_category": "국회",
    "deasu": "21",
    "meeting_specification": "소위원회",
    "commitee": "정무위원회-법안심사제2소위원회",
    "number_of_meetings": 405,
    "chasu": 1,
    "meeting_date": "2023년4월20일(목)"
  },
  {
    "meeting_id": 52892,
    "meeting_category": "국회",
    "deasu": "21",
    "meeting_specification": "소위원회",
    "commitee": "정무위원회-법안심사제1소위원회",
    "number_of_meetings": 405,
    "chasu": 1,
    "meeting_date": "2023년4월25일(화)"
  },
  {
    "meeting_id": 52931,
    "meeting_category": "국회",
    "deasu": "21",
    "meeting_specification": "소위원회",
    "commitee": "정무위원회-법안심사제1소위원회",
    "number_of_meetings": 406,
    "chasu": 1,
    "meeting_date": "2023년5월16일(화)"
  },
  {
    "meeting_id": 53012,
    "meeting_category": "국회",
    "deasu": "21",
    "meeting_specification": "소위원회",
    "commitee": "정무위원회-법안심사제1소위원회",
    "number_of_meetings": 407,
    "chasu": 1,
    "meeting_date": "2023년6월20일(화)"
  },
  {
    "meeting_id": 53024,
    "meeting_category": "국회",
    "deasu": "21",
    "meeting_specification": "소위원회",
    "commitee": "정무위원회-법안심사제2소위원회",
    "number_of_meetings": 407,
    "chasu": 1,
    "meeting_date": "2023년6월22일(목)"
  },
  {
    "meeting_id": 53033,
    "meeting_category": "국회",
    "deasu": "21",
    "meeting_specification": "소위원회",
    "commitee": "정무위원회-법안심사제1소위원회",
    "number_of_meetings": 407,
    "chasu": 2,
    "meeting_date": "2023년6월27일(화)"
  },
  {
    "meeting_id": 53045,
    "meeting_category": "국회",
    "deasu": "21",
    "meeting_specification": "소위원회",
    "commitee": "정무위원회-법안심사제2소위원회",
    "number_of_meetings": 407,
    "chasu": 2,
    "meeting_date": "2023년6월29일(목)"
  },
  {
    "meeting_id": 53051,
    "meeting_category": "국회",
    "deasu": "21",
    "meeting_specification": "소위원회",
    "commitee": "정무위원회-법안심사제1소위원회",
    "number_of_meetings": 407,
    "chasu": 3,
    "meeting_date": "2023년7월4일(화)"
  },
  {
    "meeting_id": 53197,
    "meeting_category": "국회",
    "deasu": "21",
    "meeting_specification": "소위원회",
    "commitee": "정무위원회-예산결산심사소위원회",
    "number_of_meetings": 410,
    "chasu": 1,
    "meeting_date": "2023년9월5일(화)"
  },
  {
    "meeting_id": 53425,
    "meeting_category": "국회",
    "deasu": "21",
    "meeting_specification": "소위원회",
    "commitee": "정무위원회-예산결산심사소위원회",
    "number_of_meetings": 410,
    "chasu": 2,
    "meeting_date": "2023년11월13일(월)"
  },
  {
    "meeting_id": 53488,
    "meeting_category": "국회",
    "deasu": "21",
    "meeting_specification": "소위원회",
    "commitee": "정무위원회-예산결산심사소위원회",
    "number_of_meetings": 410,
    "chasu": 4,
    "meeting_date": "2023년11월20일(월)"
  },
  {
    "meeting_id": 53522,
    "meeting_category": "국회",
    "deasu": "21",
    "meeting_specification": "소위원회",
    "commitee": "정무위원회-법안심사제2소위원회",
    "number_of_meetings": 410,
    "chasu": 1,
    "meeting_date": "2023년11월23일(목)"
  },
  {
    "meeting_id": 53554,
    "meeting_category": "국회",
    "deasu": "21",
    "meeting_specification": "소위원회",
    "commitee": "정무위원회-법안심사제1소위원회",
    "number_of_meetings": 410,
    "chasu": 2,
    "meeting_date": "2023년11월28일(화)"
  },
  {
    "meeting_id": 53610,
    "meeting_category": "국회",
    "deasu": "21",
    "meeting_specification": "소위원회",
    "commitee": "정무위원회-법안심사제1소위원회",
    "number_of_meetings": 410,
    "chasu": 3,
    "meeting_date": "2023년12월5일(화)"
  }
]